maleo_foundation/__init__.py
maleo_foundation/authentication.py
maleo_foundation/constants.py
maleo_foundation/controller_types.py
maleo_foundation/enums.py
maleo_foundation/extended_types.py
maleo_foundation/rest_controller_result.py
maleo_foundation/types.py
maleo_foundation/client/__init__.py
maleo_foundation/client/manager.py
maleo_foundation/client/services/__init__.py
maleo_foundation/client/services/key.py
maleo_foundation/client/services/signature.py
maleo_foundation/client/services/token.py
maleo_foundation/client/services/encryption/__init__.py
maleo_foundation/client/services/encryption/aes.py
maleo_foundation/client/services/encryption/rsa.py
maleo_foundation/client/services/hash/__init__.py
maleo_foundation/client/services/hash/bcrypt.py
maleo_foundation/client/services/hash/hmac.py
maleo_foundation/client/services/hash/sha256.py
maleo_foundation/expanded_types/__init__.py
maleo_foundation/expanded_types/client.py
maleo_foundation/expanded_types/general.py
maleo_foundation/expanded_types/hash.py
maleo_foundation/expanded_types/key.py
maleo_foundation/expanded_types/service.py
maleo_foundation/expanded_types/signature.py
maleo_foundation/expanded_types/token.py
maleo_foundation/expanded_types/encryption/__init__.py
maleo_foundation/expanded_types/encryption/aes.py
maleo_foundation/expanded_types/encryption/rsa.py
maleo_foundation/managers/__init__.py
maleo_foundation/managers/cache.py
maleo_foundation/managers/configuration.py
maleo_foundation/managers/credential.py
maleo_foundation/managers/db.py
maleo_foundation/managers/middleware.py
maleo_foundation/managers/service.py
maleo_foundation/managers/client/__init__.py
maleo_foundation/managers/client/base.py
maleo_foundation/managers/client/maleo.py
maleo_foundation/managers/client/google/__init__.py
maleo_foundation/managers/client/google/base.py
maleo_foundation/managers/client/google/parameter.py
maleo_foundation/managers/client/google/secret.py
maleo_foundation/managers/client/google/storage.py
maleo_foundation-0.3.76.dist-info/METADATA
maleo_foundation-0.3.76.dist-info/WHEEL
maleo_foundation-0.3.76.dist-info/top_level.txt
maleo_foundation-0.3.76.dist-info/RECORD
