Metadata-Version: 2.4
Name: maleo_foundation
Version: 0.3.76
Summary: Foundation package for Maleo
Author-email: Agra Bima Yuda <agra@nexmedis.com>
License: MIT
Requires-Python: >=3.7
Requires-Dist: aiocache>=0.12.3
Requires-Dist: aioredis>=2.0.1
Requires-Dist: annotated-types>=0.7.0
Requires-Dist: anyio>=4.9.0
Requires-Dist: async-timeout>=5.0.1
Requires-Dist: bcrypt>=4.3.0
Requires-Dist: black>=25.1.0
Requires-Dist: build>=1.2.2.post1
Requires-Dist: cachetools>=5.5.2
Requires-Dist: certifi>=2025.1.31
Requires-Dist: cffi>=1.17.1
Requires-Dist: cfgv>=3.4.0
Requires-Dist: charset-normalizer>=3.4.1
Requires-Dist: click>=8.1.8
Requires-Dist: cryptography>=44.0.2
Requires-Dist: Deprecated>=1.2.18
Requires-Dist: distlib>=0.3.9
Requires-Dist: docutils>=0.21.2
Requires-Dist: fastapi>=0.115.12
Requires-Dist: filelock>=3.18.0
Requires-Dist: google-api-core>=2.24.2
Requires-Dist: google-auth>=2.39.0
Requires-Dist: google-cloud-appengine-logging>=1.6.1
Requires-Dist: google-cloud-audit-log>=0.3.2
Requires-Dist: google-cloud-core>=2.4.3
Requires-Dist: google-cloud-logging>=3.12.0
Requires-Dist: google-cloud-parametermanager>=0.1.3
Requires-Dist: google-cloud-pubsub>=2.30.0
Requires-Dist: google-cloud-secret-manager>=2.23.3
Requires-Dist: google-cloud-storage>=2.19.0
Requires-Dist: google-crc32c>=1.7.1
Requires-Dist: google-resumable-media>=2.7.2
Requires-Dist: googleapis-common-protos>=1.70.0
Requires-Dist: greenlet>=3.2.0
Requires-Dist: grpc-google-iam-v1>=0.14.2
Requires-Dist: grpcio>=1.71.0
Requires-Dist: grpcio-status>=1.71.0
Requires-Dist: h11>=0.14.0
Requires-Dist: httpcore>=1.0.8
Requires-Dist: httpx>=0.28.1
Requires-Dist: id>=1.5.0
Requires-Dist: identify>=2.6.12
Requires-Dist: idna>=3.10
Requires-Dist: importlib_metadata>=8.6.1
Requires-Dist: jaraco.classes>=3.4.0
Requires-Dist: jaraco.context>=6.0.1
Requires-Dist: jaraco.functools>=4.1.0
Requires-Dist: jeepney>=0.9.0
Requires-Dist: keyring>=25.6.0
Requires-Dist: markdown-it-py>=3.0.0
Requires-Dist: mdurl>=0.1.2
Requires-Dist: more-itertools>=10.6.0
Requires-Dist: mypy_extensions>=1.1.0
Requires-Dist: nh3>=0.2.21
Requires-Dist: nodeenv>=1.9.1
Requires-Dist: opentelemetry-api>=1.34.1
Requires-Dist: opentelemetry-sdk>=1.34.1
Requires-Dist: opentelemetry-semantic-conventions>=0.55b1
Requires-Dist: packaging>=24.2
Requires-Dist: pathspec>=0.11.1
Requires-Dist: platformdirs>=4.3.0
Requires-Dist: pluggy>=1.6.0
Requires-Dist: pre_commit>=4.2.0
Requires-Dist: proto-plus>=1.26.1
Requires-Dist: protobuf>=5.29.4
Requires-Dist: pyasn1>=0.6.1
Requires-Dist: pyasn1_modules>=0.4.2
Requires-Dist: pycparser>=2.22
Requires-Dist: pycryptodome>=3.22.0
Requires-Dist: pydantic>=2.11.3
Requires-Dist: pydantic-settings>=2.9.1
Requires-Dist: pydantic_core>=2.33.1
Requires-Dist: Pygments>=2.19.1
Requires-Dist: PyJWT>=2.10.1
Requires-Dist: pyproject_hooks>=1.2.0
Requires-Dist: python-dotenv>=1.1.0
Requires-Dist: PyYAML>=6.0.2
Requires-Dist: readme_renderer>=44.0
Requires-Dist: redis>=6.1.0
Requires-Dist: requests>=2.32.3
Requires-Dist: requests-toolbelt>=1.0.0
Requires-Dist: rfc3986>=2.0.0
Requires-Dist: rich>=14.0.0
Requires-Dist: rsa>=4.9.1
Requires-Dist: ruff>=0.12.2
Requires-Dist: SecretStorage>=3.3.3
Requires-Dist: sniffio>=1.3.1
Requires-Dist: SQLAlchemy>=2.0.40
Requires-Dist: starlette>=0.46.2
Requires-Dist: twine>=6.1.0
Requires-Dist: typing-inspection>=0.4.0
Requires-Dist: typing_extensions>=4.13.2
Requires-Dist: ua-parser>=1.0.1
Requires-Dist: ua-parser-builtins>=0.18.0.post1
Requires-Dist: urllib3>=2.4.0
Requires-Dist: user-agents>=2.2.0
Requires-Dist: uvicorn>=0.34.2
Requires-Dist: virtualenv>=20.31.2
Requires-Dist: wrapt>=1.17.2
Requires-Dist: zipp>=3.21.0
